Library/DataProfileAKP.py
Library/__init__.py
DataProfilingAKP-0.1.1.dist-info/METADATA
DataProfilingAKP-0.1.1.dist-info/WHEEL
DataProfilingAKP-0.1.1.dist-info/top_level.txt
DataProfilingAKP-0.1.1.dist-info/RECORD
