Metadata-Version: 2.1
Name: DataProfilingAKP
Version: 0.1.1
Summary: Data Profiler Library
Author: Abhijeet Subhash Kasab
Author-email: abhijeetkasab07@gmail.com
License: The Unlicense
Requires-Python: >=3.7
